aerofiles/errors.py
aerofiles/__init__.py
aerofiles/seeyou/__init__.py
aerofiles/seeyou/reader.py
aerofiles/seeyou/converter.py
aerofiles/igc/patterns.py
aerofiles/igc/__init__.py
aerofiles/igc/writer.py
aerofiles/util/units.py
aerofiles/util/__init__.py
aerofiles/welt2000/__init__.py
aerofiles/welt2000/reader.py
aerofiles/welt2000/converter.py
aerofiles-0.1.1.dist-info/top_level.txt
aerofiles-0.1.1.dist-info/pydist.json
aerofiles-0.1.1.dist-info/RECORD
aerofiles-0.1.1.dist-info/METADATA
aerofiles-0.1.1.dist-info/DESCRIPTION.rst
aerofiles-0.1.1.dist-info/WHEEL
