Metadata-Version: 2.0
Name: aerofiles
Version: 0.1.1
Summary: waypoint, task and tracklog file readers and writers for aviators
Home-page: https://github.com/Turbo87/aerofiles/
Author: Tobias Bieniek
Author-email: tobias.bieniek@gmx.de
License: MIT
Platform: UNKNOWN
Classifier: Development Status :: 1 - Planning
Classifier: Intended Audience :: Developers
Classifier: License :: OSI Approved :: MIT License
Classifier: Natural Language :: English
Classifier: Operating System :: OS Independent
Classifier: Programming Language :: Python
Classifier: Topic :: Scientific/Engineering :: GIS
